[{"DocumentTypeId":"DocumentExtraction.DocumentType.Invoices","Keywords":[{"Values":["invoice","account"],"NumberOfTimesConfirmed":1,"LastUpdated":"2024-08-30T21:51:04.705709+05:30"},{"Values":["in","voice"],"NumberOfTimesConfirmed":1,"LastUpdated":"2024-08-30T21:51:04.7059187+05:30"},{"Values":["invoice"],"NumberOfTimesConfirmed":2,"LastUpdated":"2024-08-31T05:03:19.5546111+05:30"}]},{"DocumentTypeId":"DocumentExtraction.DocumentType.Reciepts","Keywords":[{"Values":["server"],"NumberOfTimesConfirmed":1,"LastUpdated":"2024-08-30T21:51:04.706383+05:30"},{"Values":["check","server:","total:"],"NumberOfTimesConfirmed":1,"LastUpdated":"2024-08-31T05:32:57.6011273+05:30"},{"Values":["server:","date:","table:","total:"],"NumberOfTimesConfirmed":1,"LastUpdated":"2024-08-31T05:38:17.360937+05:30"},{"Values":["date:","table:","total:"],"NumberOfTimesConfirmed":1,"LastUpdated":"2024-08-31T05:43:46.7488124+05:30"},{"Values":["check","server:","table:","total:"],"NumberOfTimesConfirmed":3,"LastUpdated":"2024-08-31T05:47:06.1180728+05:30"}]}]
